{
    "Brown_Butter_Chocolate_Chip": {
        "Name": "Brown Butter Chocolate Chip",
        "Emoji": "🍪",
        "Price": 0.0,
        "DisplayPrice": "$15.00 - $25.00",
        "Image": "Brown_Butter_Chocolate_Chip.jpg",
        "Route": "/Item/Brown_Butter_Chocolate_Chip",
        "Tags": ["🍪 Cookie"],
        "Alternative": "Brown Butter Chocolate Chip Cookies",
        "Options": [
            {
                "price": 15.0,
                "description": "Six cookies"
            },
            {
                "price": 25.0,
                "description": "Twelve cookies"
            }
        ]
    },
    "Sugar": {
        "Name": "Sugar Cookies",
        "Emoji": "🍪",
        "Price": 0.0,
        "DisplayPrice": "$15.00 - $25.00",
        "Image": "Sugar.jpg",
        "Route": "/Item/Sugar",
        "Tags": ["🍪 Cookie"],
        "Alternative": "",
        "Options": [
            {
                "price": 15.0,
                "description": "Six cookies"
            },
            {
                "price": 25.0,
                "description": "Twelve cookies"
            }
        ]
    },
    "Snickerdoodle": {
        "Name": "Snickerdoodles",
        "Emoji": "🍪",
        "Price": 0.0,
        "DisplayPrice": "$15.00 - $25.00",
        "Image": "Snickerdoodle.jpg",
        "Route": "/Item/Snickerdoodle",
        "Tags": ["🍪 Cookie"],
        "Alternative": "Snickerdoodle Cookies",
        "Options": [
            {
                "price": 15.0,
                "description": "Six cookies"
            },
            {
                "price": 25.0,
                "description": "Twelve cookies"
            }
        ]
    },
    "Ginger_Molasses": {
        "Name": "Ginger Molasses Cookies",
        "Emoji": "🍪",
        "Price": 0.0,
        "DisplayPrice": "$15.00 - $25.00",
        "Image": "Ginger_Molasses.jpg",
        "Route": "/Item/Ginger_Molasses",
        "Tags": ["🍪 Cookie"],
        "Alternative": "",
        "Options": [
            {
                "price": 15.0,
                "description": "Six cookies"
            },
            {
                "price": 25.0,
                "description": "Twelve cookies"
            }
        ]
    },
    "Double_Chocolate": {
        "Name": "Double Chocolate Cookies",
        "Emoji": "🍪",
        "Price": 0.0,
        "DisplayPrice": "$15.00 - $25.00",
        "Image": "Double_Chocolate.jpg",
        "Route": "/Item/Double_Chocolate",
        "Tags": ["🍪 Cookie"],
        "Alternative": "",
        "Options": [
            {
                "price": 15.0,
                "description": "Six cookies"
            },
            {
                "price": 25.0,
                "description": "Twelve cookies"
            }
        ]
    },
    "Fudge_Brownies": {
        "Name": "Fudge Brownies",
        "Emoji": "🍫",
        "Price": 0.0,
        "DisplayPrice": "$15.00",
        "Image": "Fudge_Brownies.jpg",
        "Route": "/Item/Fudge_Brownies",
        "Tags": ["🍫 Brownie"],
        "Alternative": "",
        "Options": [
            {
                "price": 15.0,
                "description": "One Pan"
            }
        ]
    },
    "Smores_Brownies": {
        "Name": "S'mores Brownies",
        "Emoji": "☁️",
        "Price": 0.0,
        "DisplayPrice": "$15.00",
        "Image": "Smores_Brownies.jpg",
        "Route": "/Item/Smores_Brownies",
        "Tags": ["🍫 Brownie"],
        "Alternative": "Smore Brownies, Smores Brownies",
        "Options": [
            {
                "price": 15.0,
                "description": "One Pan"
            }
        ]
    },
    "Caramel_Pretzel_Brownies": {
        "Name": "Caramel Pretzel Brownies",
        "Emoji": "🥨",
        "Price": 0.0,
        "DisplayPrice": "$15.00",
        "Image": "Caramel_Pretzel_Brownies.jpg",
        "Route": "/Item/Caramel_Pretzel_Brownies",
        "Tags": ["🍫 Brownie"],
        "Alternative": "",
        "Options": [
            {
                "price": 15.0,
                "description": "One Pan"
            }
        ]
    },
    "Crunchy_Italian_Loaf": {
        "Name": "Crunchy Italian Loaf",
        "Emoji": "🥖",
        "Price": 0.0,
        "DisplayPrice": "$12.00",
        "Image": "Crunchy_Italian_Loaf.jpg",
        "Route": "/Item/Crunchy_Italian_Loaf",
        "Tags": ["🥖 Bread"],
        "Alternative": "Crunchy Italian Bread, Italian Bread",
        "Options": [
            {
                "price": 12.0,
                "description": "One Loaf"
            }
        ]
    },
    "Everything_Bagel": {
        "Name": "Everything Bagels",
        "Emoji": "🥯",
        "Price": 0.0,
        "DisplayPrice": "$20.00 - $30.00",
        "Image": "Everything_Bagel.jpg",
        "Route": "/Item/Everything_Bagel",
        "Tags": ["🥯 Bagel", "🥖 Bread"],
        "Alternative": "",
        "Options": [
            {
                "price": 20.0,
                "description": "Eight Bagels"
            },
            {
                "price": 30.0,
                "description": "Sixteen Bagels"
            }
        ]
    },
    "Plain_Bagel": {
        "Name": "Plain Bagels",
        "Emoji": "🥯",
        "Price": 0.0,
        "DisplayPrice": "$20.00 - $30.00",
        "Image": "Plain_Bagel.jpg",
        "Route": "/Item/Plain_Bagel",
        "Tags": ["🥯 Bagel", "🥖 Bread"],
        "Alternative": "",
        "Options": [
            {
                "price": 20.0,
                "description": "Eight Bagels"
            },
            {
                "price": 30.0,
                "description": "Sixteen Bagels"
            }
        ]
    },
    "Cinnamon_Sugar": {
        "Name": "Cinnamon Sugar",
        "Emoji": "🥯",
        "Price": 0.0,
        "DisplayPrice": "$20.00 - $30.00",
        "Image": "Cinnamon_Sugar.jpg",
        "Route": "/Item/Cinnamon_Sugar",
        "Tags": ["🥯 Bagel", "🥖 Bread"],
        "Alternative": "Cinnamon Sugar Bagels",
        "Options": [
            {
                "price": 20.0,
                "description": "Eight Bagels"
            },
            {
                "price": 30.0,
                "description": "Sixteen Bagels"
            }
        ]
    },
    "Chocolate_Cake": {
        "Name": "Chocolate Cake",
        "Emoji": "🎂",
        "Price": 0.0,
        "DisplayPrice": "$15.00",
        "Image": "Chocolate_Cake.jpg",
        "Route": "/Item/Chocolate_Cake",
        "Tags": ["🎂 Cake"],
        "Alternative": "",
        "Options": [
            {
                "price": 15.0,
                "description": "One Cake"
            }
        ]
    },
    "Vanilla_Cake": {
        "Name": "Vanilla Cake",
        "Emoji": "🎂",
        "Price": 0.0,
        "DisplayPrice": "$15.00",
        "Image": "Vanilla_Cake.jpg",
        "Route": "/Item/Vanilla_Cake",
        "Tags": ["🎂 Cake"],
        "Alternative": "",
        "Options": [
            {
                "price": 15.0,
                "description": "One Cake"
            }
        ]
    }
}